medspacy/__init__.py
medspacy/_extensions.py
medspacy/_version.py
medspacy/components.py
medspacy/custom_tokenizer.py
medspacy/ner.py
medspacy/sentence_splitting.py
medspacy/util.py
medspacy/visualization.py
medspacy/common/__init__.py
medspacy/common/base_rule.py
medspacy/common/medspacy_matcher.py
medspacy/common/regex_matcher.py
medspacy/common/util.py
medspacy/context/__init__.py
medspacy/context/context.py
medspacy/context/context_graph.py
medspacy/context/context_modifier.py
medspacy/context/context_rule.py
medspacy/context/util.py
medspacy/io/__init__.py
medspacy/io/config_example.py
medspacy/io/db.py
medspacy/io/db_connect.py
medspacy/io/db_reader.py
medspacy/io/db_writer.py
medspacy/io/doc_consumer.py
medspacy/io/pipeline.py
medspacy/postprocess/__init__.py
medspacy/postprocess/postprocessing_functions.py
medspacy/postprocess/postprocessing_pattern.py
medspacy/postprocess/postprocessing_rule.py
medspacy/postprocess/postprocessor.py
medspacy/preprocess/__init__.py
medspacy/preprocess/preprocessing_rule.py
medspacy/preprocess/preprocessor.py
medspacy/section_detection/__init__.py
medspacy/section_detection/section.py
medspacy/section_detection/section_rule.py
medspacy/section_detection/sectionizer.py
medspacy/section_detection/util.py
medspacy/target_matcher/__init__.py
medspacy/target_matcher/concept_tagger.py
medspacy/target_matcher/target_matcher.py
medspacy/target_matcher/target_rule.py
resources/context_rules.json
resources/rush_rules.tsv
resources/section_patterns.json
resources/quickumls/QuickUMLS_SAMPLE_lowercase_POSIX_unqlite/README.md
resources/quickumls/QuickUMLS_SAMPLE_lowercase_POSIX_unqlite/database_backend.flag
resources/quickumls/QuickUMLS_SAMPLE_lowercase_POSIX_unqlite/language.flag
resources/quickumls/QuickUMLS_SAMPLE_lowercase_POSIX_unqlite/lowercase.flag
resources/quickumls/QuickUMLS_SAMPLE_lowercase_POSIX_unqlite/normalize-unicode.flag
resources/quickumls/QuickUMLS_SAMPLE_lowercase_POSIX_unqlite/cui-semtypes.db/cui.unqlite
medspacy-1.0.0.dist-info/LICENSE
medspacy-1.0.0.dist-info/METADATA
medspacy-1.0.0.dist-info/WHEEL
medspacy-1.0.0.dist-info/top_level.txt
medspacy-1.0.0.dist-info/RECORD
