Metadata-Version: 2.1
Name: medspacy
Version: 1.0.0
Summary: Library for clinical NLP with spaCy.
Author: medSpaCy
License-File: LICENSE
Requires-Dist: spacy (>=3.4.1)
Requires-Dist: PyRuSH (>=1.0.6)
Requires-Dist: pysbd (==0.3.4)
Requires-Dist: jsonschema
Requires-Dist: medspacy-quickumls (==2.6)
